jupyterlab_pkm/__init__.py
jupyterlab_pkm/_version.py
jupyterlab_pkm/labextension/package.json
jupyterlab_pkm/labextension/schemas/@jupyterlab/pkm-extension/package.json.orig
jupyterlab_pkm/labextension/static/665.4a923319198623724d16.js
jupyterlab_pkm/labextension/static/775.418fe5d4fddb4b929c2e.js
jupyterlab_pkm/labextension/static/remoteEntry.d4865e2b13e73fd47cbe.js
jupyterlab_pkm/labextension/static/style.js
jupyterlab_pkm/labextension/static/third-party-licenses.json
share/jupyter/labextensions/@jupyterlab/pkm-extension/package.json
share/jupyter/labextensions/@jupyterlab/pkm-extension/schemas/@jupyterlab/pkm-extension/package.json.orig
share/jupyter/labextensions/@jupyterlab/pkm-extension/static/665.4a923319198623724d16.js
share/jupyter/labextensions/@jupyterlab/pkm-extension/static/775.418fe5d4fddb4b929c2e.js
share/jupyter/labextensions/@jupyterlab/pkm-extension/static/remoteEntry.d4865e2b13e73fd47cbe.js
share/jupyter/labextensions/@jupyterlab/pkm-extension/static/style.js
share/jupyter/labextensions/@jupyterlab/pkm-extension/static/third-party-licenses.json
jupyterlab_pkm-0.1.12.data/data/share/jupyter/labextensions/@jupyterlab/pkm-extension/package.json
jupyterlab_pkm-0.1.12.data/data/share/jupyter/labextensions/@jupyterlab/pkm-extension/schemas/@jupyterlab/pkm-extension/package.json.orig
jupyterlab_pkm-0.1.12.data/data/share/jupyter/labextensions/@jupyterlab/pkm-extension/static/665.4a923319198623724d16.js
jupyterlab_pkm-0.1.12.data/data/share/jupyter/labextensions/@jupyterlab/pkm-extension/static/775.418fe5d4fddb4b929c2e.js
jupyterlab_pkm-0.1.12.data/data/share/jupyter/labextensions/@jupyterlab/pkm-extension/static/remoteEntry.d4865e2b13e73fd47cbe.js
jupyterlab_pkm-0.1.12.data/data/share/jupyter/labextensions/@jupyterlab/pkm-extension/static/style.js
jupyterlab_pkm-0.1.12.data/data/share/jupyter/labextensions/@jupyterlab/pkm-extension/static/third-party-licenses.json
jupyterlab_pkm-0.1.12.dist-info/METADATA
jupyterlab_pkm-0.1.12.dist-info/WHEEL
jupyterlab_pkm-0.1.12.dist-info/licenses/LICENSE
jupyterlab_pkm-0.1.12.dist-info/RECORD
