Metadata-Version: 2.4
Name: jupyterlab_pkm
Version: 0.1.12
Summary: Personal Knowledge Management extension for JupyterLab Desktop
Project-URL: Homepage, https://github.com/XLabCU/jupyterlab-desktop-pkm
Project-URL: Bug Tracker, https://github.com/XLabCU/jupyterlab-desktop-pkm/issues
Project-URL: Repository, https://github.com/XLabCU/jupyterlab-desktop-pkm.git
Author: Shawn Graham
License: BSD 3-Clause License
License-File: LICENSE
Keywords: backlinks,extension,jupyter,jupyterlab,knowledge-management,pkm,wikilinks
Classifier: Framework :: Jupyter
Classifier: Framework :: Jupyter :: JupyterLab
Classifier: Framework :: Jupyter :: JupyterLab :: 4
Classifier: Framework :: Jupyter :: JupyterLab :: Extensions
Classifier: Framework :: Jupyter :: JupyterLab :: Extensions :: Prebuilt
Classifier: License :: OSI Approved :: BSD License
Classifier: Programming Language :: Python
Classifier: Programming Language :: Python :: 3
Classifier: Programming Language :: Python :: 3.9
Classifier: Programming Language :: Python :: 3.10
Classifier: Programming Language :: Python :: 3.11
Classifier: Programming Language :: Python :: 3.12
Classifier: Programming Language :: Python :: 3.13
Requires-Python: >=3.9
